MANIFEST.in
README.rst
setup.cfg
setup.py
pylm/registry/__init__.py
pylm/registry/application.py
pylm/registry/runner.py
pylm/registry/clients/__init__.py
pylm/registry/clients/logs.py
pylm/registry/clients/registry.py
pylm/registry/handlers/__init__.py
pylm/registry/handlers/admin.py
pylm/registry/handlers/base.py
pylm/registry/handlers/cluster.py
pylm/registry/handlers/dashboard.py
pylm/registry/handlers/index.py
pylm/registry/handlers/login.py
pylm/registry/handlers/logs.py
pylm/registry/handlers/manager.py
pylm/registry/handlers/static.py
pylm/registry/handlers/persistency/__init__.py
pylm/registry/handlers/persistency/db.py
pylm/registry/handlers/persistency/models.py
pylm/registry/messages/__init__.py
pylm/registry/messages/registry_pb2.py
pylm/registry/static/cluster.conf
pylm/registry/static/echo_cluster.conf
pylm/registry/static/echoer.py
pylm/registry/static/favicon.ico
pylm/registry/static/node1.conf
pylm/registry/static/node2.conf
pylm/registry/templates/cluster.html
pylm/registry/templates/dashboard.html
pylm/registry/templates/index.html
pylm/registry/templates/new_cluster.html
pylm/registry/templates/new_user.html
pylm/registry/templates/view_cluster.html
pylm/registry/templates/view_logs.html
pylm_registry.egg-info/PKG-INFO
pylm_registry.egg-info/SOURCES.txt
pylm_registry.egg-info/dependency_links.txt
pylm_registry.egg-info/entry_points.txt
pylm_registry.egg-info/namespace_packages.txt
pylm_registry.egg-info/requires.txt
pylm_registry.egg-info/top_level.txt