Metadata-Version: 1.1
Name: pylm-registry
Version: 0.4.13
Summary: Registry service to configure clusters of PALM components
Home-page: UNKNOWN
Author: See AUTHORS file
Author-email: solutions@nfq.es
License: UNKNOWN
Platform: UNKNOWN
Classifier: Development Status :: 3 - Alpha
Classifier: Environment :: Console
Classifier: Intended Audience :: Developers
Classifier: Operating System :: POSIX
Classifier: License :: OSI Approved :: GNU Affero General Public License v3
Classifier: Programming Language :: Python :: 3
Classifier: Programming Language :: Python :: 3.4
Classifier: Programming Language :: Python :: 3.5
Classifier: Programming Language :: Python :: 3.6
